{
  "_cts": {
    "homepage": {
      "title": {
        "config": {
          "patternType": "HEADING",
          "blocks": 1
        }
      }
    },
    "page": {
      "title": {
        "config": {
          "patternType": "HEADING",
          "blocks": 1
        }
      }
    },
    "blog_homepage": {
      "title": {
        "config": {
          "patternType": "HEADING",
          "blocks": 1
        }
      }
    },
    "blog_post": {
      "title": {
        "config": {
          "patternType": "HEADING",
          "blocks": 1
        }
      }
    },
    "dev_mother": {
      "title": {
        "config": {
          "patternType": "HEADING",
          "blocks": 1
        }
      }
    },
    "dev_child": {
      "title": {
        "config": {
          "patternType": "HEADING",
          "blocks": 1
        }
      }
    },
    "seo_mother": {
      "title": {
        "config": {
          "patternType": "HEADING",
          "blocks": 1
        }
      }
    },
    "seo_child": {
      "title": {
        "config": {
          "patternType": "HEADING",
          "blocks": 1
        }
      }
    }
  },
  "slices": {
    "Faq": {},
    "HeroHome": {
      "default": {
        "primary": {}
      }
    },
    "PartnersLine": {
      "default": {
        "items": {},
        "primary": {
          "title": {
            "config": {
              "patternType": "HEADING",
              "blocks": 1
            }
          }
        }
      }
    },
    "CtaHorizontal": {},
    "Testimonials": {},
    "HeroStandard": {},
    "TextBoxLight": {},
    "ImageAlone": {},
    "ImageFeaturedLeft": {
      "default": {
        "items": {
          "paragraph": {
            "config": {
              "patternType": "PARAGRAPH",
              "blocks": 1
            }
          }
        },
        "primary": {
          "title": {
            "config": {
              "patternType": "HEADING",
              "blocks": 1
            }
          }
        }
      }
    },
    "ImageFeaturedRight": {},
    "BlogPostsList": {},
    "PartnersSeo": {},
    "PartnersDev": {},
    "PartnersSliderDev": {},
    "PartnersSliderSeo": {},
    "VideoPlayer": {},
    "TextContent": {
      "default": {
        "primary": {},
        "items": {
          "content_box": {
            "config": {
              "patternType": "PARAGRAPH",
              "blocks": 1
            }
          }
        }
      }
    }
  }
}