{
  "title": {
    "__TYPE__": "StructuredTextContent",
    "value": [
      {
        "type": "heading1",
        "content": {
          "text": "Stone"
        }
      }
    ]
  },
  "image_featured": {
    "__TYPE__": "ImageContent",
    "origin": {
      "id": "main",
      "url": "https://images.unsplash.com/photo-1448932223592-d1fc686e76ea",
      "width": 3500,
      "height": 2338
    },
    "url": "https://images.unsplash.com/photo-1448932223592-d1fc686e76ea",
    "width": 3500,
    "height": 2338,
    "edit": {
      "zoom": 1,
      "crop": {
        "x": 0,
        "y": 0
      },
      "background": "transparent"
    },
    "thumbnails": {}
  },
  "excerpt": {
    "__TYPE__": "FieldContent",
    "value": "by",
    "type": "Text"
  },
  "slices": {
    "__TYPE__": "SliceContentType",
    "value": [
      {
        "key": "blog_posts_list$b7865d08-8610-4f89-9151-86dcb9e89396",
        "name": "blog_posts_list",
        "widget": {
          "__TYPE__": "SharedSliceContent",
          "variation": "default",
          "primary": {
            "title": {
              "__TYPE__": "StructuredTextContent",
              "value": [
                {
                  "type": "heading1",
                  "content": {
                    "text": "Eventually"
                  }
                }
              ]
            },
            "description": {
              "__TYPE__": "StructuredTextContent",
              "value": [
                {
                  "type": "paragraph",
                  "content": {
                    "text": "Aute commodo deserunt duis ullamco occaecat ea nulla esse irure sint nostrud."
                  }
                }
              ]
            }
          },
          "items": [
            {
              "__TYPE__": "GroupItemContent",
              "value": []
            }
          ]
        }
      },
      {
        "key": "cta_horizontal$e1ffe1d5-d580-4c7b-8e8d-daf7a84cd346",
        "name": "cta_horizontal",
        "widget": {
          "__TYPE__": "SharedSliceContent",
          "variation": "default",
          "primary": {
            "title": {
              "__TYPE__": "StructuredTextContent",
              "value": [
                {
                  "type": "heading1",
                  "content": {
                    "text": "Limited"
                  }
                }
              ]
            },
            "description": {
              "__TYPE__": "StructuredTextContent",
              "value": [
                {
                  "type": "paragraph",
                  "content": {
                    "text": "Ad sint aliquip irure voluptate enim ea ullamco culpa velit cupidatat magna laboris. Incididunt eu do aute laboris dolore occaecat occaecat esse duis id ut qui magna voluptate pariatur."
                  }
                }
              ]
            }
          },
          "items": [
            {
              "__TYPE__": "GroupItemContent",
              "value": []
            }
          ]
        }
      },
      {
        "key": "image_alone$eb0399f8-63b8-407f-9deb-a9c9e583c8e8",
        "name": "image_alone",
        "widget": {
          "__TYPE__": "SharedSliceContent",
          "variation": "default",
          "primary": {
            "title": {
              "__TYPE__": "StructuredTextContent",
              "value": [
                {
                  "type": "heading1",
                  "content": {
                    "text": "Furniture"
                  }
                }
              ]
            },
            "description": {
              "__TYPE__": "StructuredTextContent",
              "value": [
                {
                  "type": "paragraph",
                  "content": {
                    "text": "Do fugiat cupidatat enim enim pariatur nulla proident ad."
                  }
                }
              ]
            }
          },
          "items": [
            {
              "__TYPE__": "GroupItemContent",
              "value": []
            }
          ]
        }
      },
      {
        "key": "faq$3758e9f3-1f23-46be-9ded-9d04375a9b09",
        "name": "faq",
        "widget": {
          "__TYPE__": "SharedSliceContent",
          "variation": "default",
          "primary": {
            "title": {
              "__TYPE__": "StructuredTextContent",
              "value": [
                {
                  "type": "heading1",
                  "content": {
                    "text": "Shadow"
                  }
                }
              ]
            },
            "description": {
              "__TYPE__": "StructuredTextContent",
              "value": [
                {
                  "type": "paragraph",
                  "content": {
                    "text": "Duis do ad amet ipsum eiusmod incididunt Lorem eiusmod. Reprehenderit cupidatat in elit irure consectetur sunt velit elit."
                  }
                }
              ]
            }
          },
          "items": [
            {
              "__TYPE__": "GroupItemContent",
              "value": []
            }
          ]
        }
      },
      {
        "key": "hero_standard$1df234b8-9973-49b5-a8a8-fc83555433ce",
        "name": "hero_standard",
        "widget": {
          "__TYPE__": "SharedSliceContent",
          "variation": "default",
          "primary": {
            "title": {
              "__TYPE__": "StructuredTextContent",
              "value": [
                {
                  "type": "heading1",
                  "content": {
                    "text": "Diagram"
                  }
                }
              ]
            },
            "description": {
              "__TYPE__": "StructuredTextContent",
              "value": [
                {
                  "type": "paragraph",
                  "content": {
                    "text": "Ea deserunt adipisicing fugiat proident dolor et officia Lorem aliquip. Velit et amet aliquip. Eiusmod eu sit veniam voluptate irure magna dolore duis."
                  }
                }
              ]
            }
          },
          "items": [
            {
              "__TYPE__": "GroupItemContent",
              "value": []
            }
          ]
        }
      },
      {
        "key": "hero_home$eca7c33a-e40d-40f8-82bd-9668e0e8a274",
        "name": "hero_home",
        "widget": {
          "__TYPE__": "SharedSliceContent",
          "variation": "default",
          "primary": {
            "title": {
              "__TYPE__": "StructuredTextContent",
              "value": [
                {
                  "type": "heading1",
                  "content": {
                    "text": "Where"
                  }
                }
              ]
            },
            "description": {
              "__TYPE__": "StructuredTextContent",
              "value": [
                {
                  "type": "paragraph",
                  "content": {
                    "text": "Lorem in velit sunt commodo minim excepteur nulla incididunt velit deserunt ipsum."
                  }
                }
              ]
            }
          },
          "items": [
            {
              "__TYPE__": "GroupItemContent",
              "value": []
            }
          ]
        }
      },
      {
        "key": "image_featured_left$dcc26c3d-8159-4214-866b-0bc4b0f0db84",
        "name": "image_featured_left",
        "widget": {
          "__TYPE__": "SharedSliceContent",
          "variation": "default",
          "primary": {
            "title": {
              "__TYPE__": "StructuredTextContent",
              "value": [
                {
                  "type": "heading1",
                  "content": {
                    "text": "Easier"
                  }
                }
              ]
            },
            "description": {
              "__TYPE__": "StructuredTextContent",
              "value": [
                {
                  "type": "paragraph",
                  "content": {
                    "text": "Ullamco irure elit consequat et quis aliquip voluptate ipsum in esse incididunt minim tempor. Laborum ipsum ut tempor ex sunt fugiat elit ipsum tempor."
                  }
                }
              ]
            }
          },
          "items": [
            {
              "__TYPE__": "GroupItemContent",
              "value": []
            }
          ]
        }
      },
      {
        "key": "image_featured_right$510dd182-ffb6-4bc4-876e-cde668d1fc26",
        "name": "image_featured_right",
        "widget": {
          "__TYPE__": "SharedSliceContent",
          "variation": "default",
          "primary": {
            "title": {
              "__TYPE__": "StructuredTextContent",
              "value": [
                {
                  "type": "heading1",
                  "content": {
                    "text": "Becoming"
                  }
                }
              ]
            },
            "description": {
              "__TYPE__": "StructuredTextContent",
              "value": [
                {
                  "type": "paragraph",
                  "content": {
                    "text": "Consequat in ad ex amet excepteur nulla nulla in."
                  }
                }
              ]
            }
          },
          "items": [
            {
              "__TYPE__": "GroupItemContent",
              "value": []
            }
          ]
        }
      },
      {
        "key": "partners_dev$42ee9ecc-9163-4980-b9cd-25e39872b43f",
        "name": "partners_dev",
        "widget": {
          "__TYPE__": "SharedSliceContent",
          "variation": "default",
          "primary": {
            "title": {
              "__TYPE__": "StructuredTextContent",
              "value": [
                {
                  "type": "heading1",
                  "content": {
                    "text": "Baseball"
                  }
                }
              ]
            },
            "description": {
              "__TYPE__": "StructuredTextContent",
              "value": [
                {
                  "type": "paragraph",
                  "content": {
                    "text": "Ea aute ad consectetur eiusmod occaecat reprehenderit ipsum esse. Elit labore quis tempor sint quis eu nostrud. Aute culpa aliquip excepteur proident fugiat labore ut anim amet ullamco."
                  }
                }
              ]
            }
          },
          "items": [
            {
              "__TYPE__": "GroupItemContent",
              "value": []
            }
          ]
        }
      },
      {
        "key": "partners_slider_dev$79291407-030c-4287-97a9-763ef7a1c537",
        "name": "partners_slider_dev",
        "widget": {
          "__TYPE__": "SharedSliceContent",
          "variation": "default",
          "primary": {
            "title": {
              "__TYPE__": "StructuredTextContent",
              "value": [
                {
                  "type": "heading1",
                  "content": {
                    "text": "Where"
                  }
                }
              ]
            },
            "description": {
              "__TYPE__": "StructuredTextContent",
              "value": [
                {
                  "type": "paragraph",
                  "content": {
                    "text": "Cupidatat quis reprehenderit culpa dolore non ea minim Lorem proident sint ea ad occaecat. Velit mollit aliquip do occaecat."
                  }
                }
              ]
            }
          },
          "items": [
            {
              "__TYPE__": "GroupItemContent",
              "value": []
            }
          ]
        }
      },
      {
        "key": "partners_seo$95059f28-ec0c-45b4-a871-028f1507ea7d",
        "name": "partners_seo",
        "widget": {
          "__TYPE__": "SharedSliceContent",
          "variation": "default",
          "primary": {
            "title": {
              "__TYPE__": "StructuredTextContent",
              "value": [
                {
                  "type": "heading1",
                  "content": {
                    "text": "Beneath"
                  }
                }
              ]
            },
            "description": {
              "__TYPE__": "StructuredTextContent",
              "value": [
                {
                  "type": "paragraph",
                  "content": {
                    "text": "Ea sint anim labore irure."
                  }
                }
              ]
            }
          },
          "items": [
            {
              "__TYPE__": "GroupItemContent",
              "value": []
            }
          ]
        }
      },
      {
        "key": "partners_line$fb9b0718-44ea-44f6-902e-8ec6b277980e",
        "name": "partners_line",
        "widget": {
          "__TYPE__": "SharedSliceContent",
          "variation": "default",
          "primary": {
            "title": {
              "__TYPE__": "StructuredTextContent",
              "value": [
                {
                  "type": "heading1",
                  "content": {
                    "text": "Garden"
                  }
                }
              ]
            },
            "description": {
              "__TYPE__": "StructuredTextContent",
              "value": [
                {
                  "type": "paragraph",
                  "content": {
                    "text": "Culpa enim laboris adipisicing ullamco sint dolore magna nulla in aliqua est dolor non deserunt non."
                  }
                }
              ]
            }
          },
          "items": [
            {
              "__TYPE__": "GroupItemContent",
              "value": []
            }
          ]
        }
      },
      {
        "key": "partners_slider_seo$318a08c8-495c-4186-8a52-0481547f34ee",
        "name": "partners_slider_seo",
        "widget": {
          "__TYPE__": "SharedSliceContent",
          "variation": "default",
          "primary": {
            "title": {
              "__TYPE__": "StructuredTextContent",
              "value": [
                {
                  "type": "heading1",
                  "content": {
                    "text": "Behavior"
                  }
                }
              ]
            },
            "description": {
              "__TYPE__": "StructuredTextContent",
              "value": [
                {
                  "type": "paragraph",
                  "content": {
                    "text": "Cillum dolore consectetur in aliqua. Reprehenderit ut sit est magna aute. Nisi consequat esse in eiusmod laborum officia."
                  }
                }
              ]
            }
          },
          "items": [
            {
              "__TYPE__": "GroupItemContent",
              "value": []
            }
          ]
        }
      },
      {
        "key": "testimonials$14fac5f1-a45b-4f1f-8745-27b4c976083f",
        "name": "testimonials",
        "widget": {
          "__TYPE__": "SharedSliceContent",
          "variation": "default",
          "primary": {
            "title": {
              "__TYPE__": "StructuredTextContent",
              "value": [
                {
                  "type": "heading1",
                  "content": {
                    "text": "Ocean"
                  }
                }
              ]
            },
            "description": {
              "__TYPE__": "StructuredTextContent",
              "value": [
                {
                  "type": "paragraph",
                  "content": {
                    "text": "Amet anim ipsum laborum. Commodo mollit sunt aliqua excepteur. Eiusmod est dolore in exercitation sunt incididunt ad do culpa est et qui."
                  }
                }
              ]
            }
          },
          "items": [
            {
              "__TYPE__": "GroupItemContent",
              "value": []
            }
          ]
        }
      },
      {
        "key": "text_box_light$a50924ee-4265-405b-83df-3174e86ee493",
        "name": "text_box_light",
        "widget": {
          "__TYPE__": "SharedSliceContent",
          "variation": "default",
          "primary": {
            "title": {
              "__TYPE__": "StructuredTextContent",
              "value": [
                {
                  "type": "heading1",
                  "content": {
                    "text": "Remarkable"
                  }
                }
              ]
            },
            "description": {
              "__TYPE__": "StructuredTextContent",
              "value": [
                {
                  "type": "paragraph",
                  "content": {
                    "text": "Proident sunt magna excepteur laboris irure aliqua nulla sunt esse ipsum eiusmod nostrud. Velit commodo duis occaecat aute esse."
                  }
                }
              ]
            }
          },
          "items": [
            {
              "__TYPE__": "GroupItemContent",
              "value": []
            }
          ]
        }
      },
      {
        "key": "video_player$fd670a6a-60dc-4350-9db9-9702f9d2c0ba",
        "name": "video_player",
        "widget": {
          "__TYPE__": "SharedSliceContent",
          "variation": "default",
          "primary": {
            "title": {
              "__TYPE__": "StructuredTextContent",
              "value": [
                {
                  "type": "heading1",
                  "content": {
                    "text": "Jungle"
                  }
                }
              ]
            },
            "description": {
              "__TYPE__": "StructuredTextContent",
              "value": [
                {
                  "type": "paragraph",
                  "content": {
                    "text": "Velit veniam in proident esse qui ut Lorem. Non fugiat ex nulla adipisicing id adipisicing sint consectetur."
                  }
                }
              ]
            }
          },
          "items": [
            {
              "__TYPE__": "GroupItemContent",
              "value": []
            }
          ]
        }
      },
      {
        "key": "text_content$bfebbe75-4cb3-4847-ac7f-37e51dbd22f2",
        "name": "text_content",
        "widget": {
          "__TYPE__": "SharedSliceContent",
          "variation": "default",
          "primary": {},
          "items": [
            {
              "__TYPE__": "GroupItemContent",
              "value": [
                [
                  "content_box",
                  {
                    "__TYPE__": "StructuredTextContent",
                    "value": [
                      {
                        "type": "paragraph",
                        "content": {
                          "text": "Sunt veniam eu ex culpa cupidatat eu nostrud aute officia dolor sint enim elit incididunt."
                        }
                      }
                    ]
                  }
                ]
              ]
            }
          ]
        }
      }
    ]
  },
  "meta_title": {
    "__TYPE__": "FieldContent",
    "value": "shut",
    "type": "Text"
  },
  "meta_description": {
    "__TYPE__": "FieldContent",
    "value": "development",
    "type": "Text"
  },
  "og_image": {
    "__TYPE__": "ImageContent",
    "origin": {
      "id": "main",
      "url": "https://images.unsplash.com/photo-1600861194802-a2b11076bc51",
      "width": 2545,
      "height": 2545
    },
    "url": "https://images.unsplash.com/photo-1600861194802-a2b11076bc51",
    "width": 2545,
    "height": 2545,
    "edit": {
      "zoom": 1,
      "crop": {
        "x": 0,
        "y": 0
      },
      "background": "transparent"
    },
    "thumbnails": {}
  }
}