{
  "id": "cta_horizontal",
  "type": "SharedSlice",
  "name": "CtaHorizontal",
  "description": "CtaHorizontal",
  "variations": [
    {
      "id": "default",
      "name": "Default",
      "docURL": "...",
      "version": "sktwi1xtmkfgx8626",
      "description": "CtaHorizontal",
      "primary": {
        "title": {
          "type": "StructuredText",
          "config": {
            "label": "h3_title",
            "placeholder": "",
            "allowTargetBlank": true,
            "single": "heading3"
          }
        },
        "desc": {
          "type": "StructuredText",
          "config": {
            "label": "desc",
            "placeholder": "",
            "allowTargetBlank": true,
            "single": "paragraph"
          }
        },
        "cta_anchor": {
          "type": "Text",
          "config": {
            "label": "cta_anchor",
            "placeholder": ""
          }
        },
        "cta_link": {
          "type": "Link",
          "config": {
            "label": "cta_link",
            "placeholder": "",
            "select": null
          }
        }
      },
      "items": {},
      "imageUrl": "https://images.prismic.io/slice-machine/621a5ec4-0387-4bc5-9860-2dd46cbc07cd_default_ss.png?auto=compress,format"
    }
  ]
}